similarity_check/__init__.py
similarity_check/checkers.py
similarity_check/utils.py
similarity_check/tests/__init__.py
similarity_check/tests/test_sentence_tranformer_checker.py
similarity_check-0.2.12.dist-info/METADATA
similarity_check-0.2.12.dist-info/WHEEL
similarity_check-0.2.12.dist-info/licenses/LICENSE
similarity_check-0.2.12.dist-info/RECORD
