Metadata-Version: 2.1
Name: similarity_check
Version: 0.2.12
Summary: package for measuring the similarity of two texts
Author-email: meshari <meshari34343@gmail.com>
License-File: LICENSE
Classifier: License :: OSI Approved :: MIT License
Classifier: Operating System :: OS Independent
Classifier: Programming Language :: Python :: 3
Requires-Python: >=3.7
Requires-Dist: boto3
Requires-Dist: gensim
Requires-Dist: pandas
Requires-Dist: pyemd
Requires-Dist: sentence-transformers
